jupyter_inheritance/__init__.py
jupyter_inheritance-0.1.0.dist-info/LICENSE
jupyter_inheritance-0.1.0.dist-info/METADATA
jupyter_inheritance-0.1.0.dist-info/WHEEL
jupyter_inheritance-0.1.0.dist-info/top_level.txt
jupyter_inheritance-0.1.0.dist-info/RECORD
