Metadata-Version: 2.1
Name: jupyter-inheritance
Version: 0.1.0
Summary: Inherit from Jupyter kernels
Home-page: UNKNOWN
Author: Jan Cervenka
Author-email: jan.cervenka@yahoo.com
License: UNKNOWN
Platform: UNKNOWN
Requires-Python: >=3.7
License-File: LICENSE
Requires-Dist: dill (>=0.3.4)
Requires-Dist: jupyter-client (>=7.0.6)
Requires-Dist: jupyter-core (>=4.9.1)
Requires-Dist: jupyter-server (>=1.11.2)
Requires-Dist: requests
Provides-Extra: tests
Requires-Dist: pytest ; extra == 'tests'
